samtal/__init__.py
samtal/__main__.py
samtal/test_bot_factories.py
samtal/adapters/__init__.py
samtal/adapters/answer_sqlite.py
samtal/adapters/conversation_mattermost.py
samtal/adapters/conversation_web.py
samtal/adapters/test_answers_sqlite.py
samtal/adapters/test_mattermost.py
samtal/adapters/test_web.py
samtal/core/__init__.py
samtal/core/answer.py
samtal/core/bot.py
samtal/core/conversation.py
samtal/core/questions.py
samtal/core/team_members.py
samtal/core/test_bot.py
samtal/core/test_helpers.py
samtal/core/test_questions.py
samtal/core/test_team_members.py
samtal-0.0.8.dist-info/LICENSE
samtal-0.0.8.dist-info/METADATA
samtal-0.0.8.dist-info/WHEEL
samtal-0.0.8.dist-info/top_level.txt
samtal-0.0.8.dist-info/RECORD
